kuisine/__init__.py
kuisine_cli-0.1.1.dist-info/LICENSE
kuisine_cli-0.1.1.dist-info/WHEEL
kuisine_cli-0.1.1.dist-info/METADATA
kuisine_cli-0.1.1.dist-info/RECORD
