Metadata-Version: 2.1
Name: kuisine-cli
Version: 0.1.1
Summary: Command line interface for kuisine.ru
Home-page: https://github.com/yafeunteun/kuisine-cli
License: MIT
Keywords: diet,fitness,sport,nutrition,meal-planning,cli,health
Author: Yann Feunteun
Author-email: yann.feunteun@protonmail.com
Requires-Python: >=3.7,<4.0
Classifier: Environment :: Console
Classifier: License :: OSI Approved :: MIT License
Classifier: Operating System :: OS Independent
Classifier: Programming Language :: Python :: 3
Classifier: Programming Language :: Python :: 3.7
Classifier: Programming Language :: Python :: 3.8
Requires-Dist: click (>=7.0,<8.0)
Requires-Dist: requests (>=2.22.0,<3.0.0)
Project-URL: Repository, https://github.com/yafeunteun/kuisine-cli
